[
  {
    "id": "1914876956392202344",
    "text": "📚  How to use AI to learn anything faster. https://t.co/zGCZDxUZA8",
    "date": "2025-04-23T03:00:17.000Z",
    "likes": 7,
    "retweets": 1,
    "replies": 2
  },
  {
    "id": "1915025029181358264",
    "text": "Checkout this",
    "date": "2025-04-23T12:48:41.000Z",
    "likes": 3,
    "retweets": 2,
    "replies": 1
  },
  {
    "id": "1915331918884724793",
    "text": "9 best WordPress #AI plugins for #content, chatbots, and more\n   1.  AI Engine\n    2. AI Power\n    3. Elementor AI\n    4. CodeWP\n    5. Alt Text AI\n    6. Divi AI\n    7. AI Bud\n    8. Rank Math Content AI\n    9. WPBot",
    "date": "2025-04-24T09:08:09.000Z",
    "likes": 1,
    "retweets": 0,
    "replies": 0
  },
  {
    "id": "1914746346965516656",
    "text": "Want to save webpages and articles offline? Check out Obsidian Clipper. A browser extension that lets you easily save web pages and articles for later reading 👉 obsidian. md/clipper https://t.co/r08nSipJQr",
    "date": "2025-04-22T18:21:18.000Z",
    "likes": 2,
    "retweets": 0,
    "replies": 1
  }
]